Metadata-Version: 1.1
Name: chimit
Version: 0.9.0
Summary: Fabric commands for simplifying server deployments
Home-page: https://github.com/chrisspen/chimit
Author: Chris Spencer
Author-email: chrisspen@gmail.com
License: MIT
Platform: UNKNOWN
Classifier: Development Status :: 4 - Beta
Classifier: Environment :: Console
Classifier: Intended Audience :: Developers
Classifier: Intended Audience :: System Administrators
Classifier: License :: OSI Approved :: MIT License
Classifier: Operating System :: Unix
Classifier: Operating System :: POSIX
Classifier: Programming Language :: Python
Classifier: Programming Language :: Python :: 2.7
Classifier: Programming Language :: Python :: 3.4
Classifier: Topic :: Software Development
